PyGeopack/FreeTSData.py
PyGeopack/GEOtoMAG.py
PyGeopack/GSEtoGSM.py
PyGeopack/GSEtoMAG.py
PyGeopack/GSEtoSM.py
PyGeopack/GSMtoGSE.py
PyGeopack/GSMtoSM.py
PyGeopack/GetDipoleTilt.py
PyGeopack/GetModelParams.py
PyGeopack/Globals.py
PyGeopack/LoadTSData.py
PyGeopack/MAGtoGEO.py
PyGeopack/MAGtoGSE.py
PyGeopack/MLONtoMLT.py
PyGeopack/MLTtoMLON.py
PyGeopack/ModelField.py
PyGeopack/ReadTSData.py
PyGeopack/SMtoGSE.py
PyGeopack/SMtoGSM.py
PyGeopack/SetCustParam.py
PyGeopack/ShueMP.py
PyGeopack/TraceField.py
PyGeopack/UpdateParameters.py
PyGeopack/_CFunctions.py
PyGeopack/_CalculateParameters.py
PyGeopack/_CheckFirstImport.py
PyGeopack/_CoordCode.py
PyGeopack/_DownloadTS05Data.py
PyGeopack/_ReadTab.py
PyGeopack/_SourceCompilation.py
PyGeopack/__del__.py
PyGeopack/__init__.py
PyGeopack/ct.py
PyGeopack/Coords/ConvCoords.py
PyGeopack/Coords/GEItoGEO.py
PyGeopack/Coords/GEItoGSE.py
PyGeopack/Coords/GEItoGSM.py
PyGeopack/Coords/GEItoMAG.py
PyGeopack/Coords/GEItoSM.py
PyGeopack/Coords/GEOtoGEI.py
PyGeopack/Coords/GEOtoGSE.py
PyGeopack/Coords/GEOtoGSM.py
PyGeopack/Coords/GEOtoMAG.py
PyGeopack/Coords/GEOtoSM.py
PyGeopack/Coords/GSEtoGEI.py
PyGeopack/Coords/GSEtoGEO.py
PyGeopack/Coords/GSEtoGSM.py
PyGeopack/Coords/GSEtoMAG.py
PyGeopack/Coords/GSEtoSM.py
PyGeopack/Coords/GSMtoGEI.py
PyGeopack/Coords/GSMtoGEO.py
PyGeopack/Coords/GSMtoGSE.py
PyGeopack/Coords/GSMtoMAG.py
PyGeopack/Coords/GSMtoSM.py
PyGeopack/Coords/MAGtoGEI.py
PyGeopack/Coords/MAGtoGEO.py
PyGeopack/Coords/MAGtoGSE.py
PyGeopack/Coords/MAGtoGSM.py
PyGeopack/Coords/MAGtoSM.py
PyGeopack/Coords/MLONtoMLT.py
PyGeopack/Coords/MLTtoMLON.py
PyGeopack/Coords/SMtoGEI.py
PyGeopack/Coords/SMtoGEO.py
PyGeopack/Coords/SMtoGSE.py
PyGeopack/Coords/SMtoGSM.py
PyGeopack/Coords/SMtoMAG.py
PyGeopack/Coords/_CFunctions.py
PyGeopack/Coords/__init__.py
PyGeopack/Params/FreeParams.py
PyGeopack/Params/GetDipoleTilt.py
PyGeopack/Params/GetModelParams.py
PyGeopack/Params/ReadTSData.py
PyGeopack/Params/UpdateParameters.py
PyGeopack-1.1.7.dist-info/LICENSE
PyGeopack-1.1.7.dist-info/METADATA
PyGeopack-1.1.7.dist-info/WHEEL
PyGeopack-1.1.7.dist-info/top_level.txt
PyGeopack-1.1.7.dist-info/RECORD
