Metadata-Version: 2.1
Name: PyGeopack
Version: 1.1.7
Summary: Geopack08 wrapper for Python
Home-page: https://github.com/mattkjames7/PyGeopack
Author: Matthew Knight James
Author-email: mattkjames7@gmail.com
License: UNKNOWN
Platform: UNKNOWN
Classifier: Programming Language :: Python :: 3
Classifier: License :: OSI Approved :: GNU General Public License (GPL)
Classifier: Operating System :: POSIX
Requires-Dist: DateTimeTools (>=1.1.0)
Requires-Dist: PyFileIO
Requires-Dist: RecarrayTools
Requires-Dist: kpindex (>=1.0.1)
Requires-Dist: numpy
Requires-Dist: pyomnidata (>=1.0.1)
